{
  "collectionName": "components_adress_addres",
  "info": {
    "displayName": "Addres",
    "description": ""
  },
  "options": {},
  "attributes": {
    "state": {
      "type": "enumeration",
      "enum": [
        "Amazonas",
        "Anzoátegui",
        "Apure",
        "Aragua",
        "Barinas",
        "Bolívar",
        "Carabobo",
        "Cojedes",
        "Delta Amacuro",
        "Distrito Capital",
        "Falcón",
        "Guárico",
        "Lara",
        "Mérida",
        "Miranda",
        "Monagas",
        "Nueva Esparta",
        "Portuguesa",
        "Sucre",
        "Táchira",
        "Trujillo",
        "Vargas",
        "Yaracuy",
        "Zulia"
      ],
      "required": true
    },
    "municipality": {
      "type": "enumeration",
      "enum": [
        "Amazonas",
        "Anaco",
        "Andrés Bello",
        "Antonio Díaz",
        "Aragua",
        "Arismendi",
        "Baralt",
        "Barinas",
        "Bolívar",
        "Brión",
        "Bruzual",
        "Buroz",
        "Cabrera",
        "Caracciolo Parra Olmedo",
        "Cárdenas",
        "Carirubana",
        "Carrizal",
        "Caroní",
        "Catatumbo",
        "Cedeño",
        "Colón",
        "Córdoba",
        "Cruz Salmerón Acosta",
        "Díaz",
        "Ezequiel Zamora",
        "Falcón",
        "Federación",
        "Francisco de Miranda",
        "Francisco Linares Alcántara",
        "Francisco Javier Pulgar",
        "García de Hevia",
        "Girardot",
        "Guaicaipuro",
        "Guanare",
        "Guanta",
        "Guasdualito",
        "Independencia",
        "Iribarren",
        "Isla de Toas",
        "Isla de Margarita",
        "Jiménez",
        "José Félix Ribas",
        "José Gregorio Monagas",
        "José María Semprún",
        "Juan Antonio Sotillo",
        "Juan Germán Roscio",
        "Juan José Mora",
        "Junín",
        "La Asunción",
        "La Cañada de Urdaneta",
        "La Ceiba",
        "La Dolorita",
        "La Guaira",
        "Lagunillas",
        "Lechería",
        "Lima Blanco",
        "Lobatera",
        "Los Guayos",
        "Los Salias",
        "Los Taques",
        "Luis Beltrán Prieto Figueroa",
        "Machiques de Perijá",
        "Macuro",
        "Maiquetía",
        "Mariño",
        "Maracaibo",
        "Marcano",
        "Mario Briceño Iragorry",
        "Matías Salazar",
        "Maturín",
        "Miranda",
        "Monagas",
        "Montes",
        "Montes de Oca",
        "Naguanagua",
        "Nirgua",
        "Ocumare del Tuy",
        "Ortiz",
        "Padre Chien",
        "Páez",
        "Palavecino",
        "Pampatar",
        "Panamericano",
        "Pedro Camejo",
        "Pedro Gual",
        "Peña",
        "Península de Macanao",
        "Piar",
        "Píritu",
        "Plaza",
        "Ponce",
        "Pueblos Llaneros",
        "Punceres",
        "Ribas",
        "Ricaurte",
        "Rómulo Gallegos",
        "San Antonio",
        "San Carlos",
        "San Casimiro",
        "San Diego",
        "San Fernando",
        "San Francisco",
        "San Francisco de Yare",
        "San Genaro de Boconoíto",
        "San Jacinto",
        "San Joaquín",
        "San José",
        "San Juan de Colón",
        "San Juan de los Morros",
        "San Lorenzo",
        "San Luis",
        "San Mateo",
        "San Pedro de Coche",
        "San Pedro de los Altos",
        "San Rafael de Onoto",
        "San Sebastián",
        "Santa Ana",
        "Santa Bárbara",
        "Santa Cruz de Mara",
        "Santa Lucía",
        "Santa Rita",
        "Santa Rosa",
        "Santiago Mariño",
        "Sifontes",
        "Simón Bolívar",
        "Simón Rodríguez",
        "Sucre",
        "Táchira",
        "Tinaquillo",
        "Tocopero",
        "Torbes",
        "Tovar",
        "Tucacas",
        "Tucupita",
        "Turen",
        "Urdaneta",
        "Valencia",
        "Valera",
        "Valle de la Pascua",
        "Vargas",
        "Veroes",
        "Villa Bruzual",
        "Villa de Cura",
        "Yaracuy",
        "Zamora",
        "Zea"
      ],
      "required": true
    },
    "Addres": {
      "type": "text",
      "required": true
    },
    "codigo_postal": {
      "type": "string",
      "required": true
    },
    "maps": {
      "type": "component",
      "repeatable": false,
      "component": "coordinates.coordenadas",
      "required": true
    }
  }
}
